<?xml version="1.0" encoding="UTF-8"?>
<model xmlns="http://www.alfresco.org/model/dictionary/1.0" name="gvis:GoogleVisionModel">
    <description>Google Vision Model</description>
    <author>keensoft</author>
    <imports>
        <import uri="http://www.alfresco.org/model/dictionary/1.0" prefix="d"/>
    </imports>
    <namespaces>
        <namespace uri="http://www.keensoft.es/model/content/google/1.0" prefix="gvis"/>
    </namespaces>
    <data-types/>
    <constraints/>
    <types/>
    <aspects>
        <aspect name="gvis:googleVision">
            <title>google.vision</title>
            <properties>
                <property name="gvis:logo">
                    <title>logo</title>
                    <type>d:text</type>
                    <mandatory>false</mandatory>
                    <index enabled="true">
                        <tokenised>TRUE</tokenised>
                        <facetable>false</facetable>
                    </index>
                </property>
                <property name="gvis:landmark">
                    <title>landmark</title>
                    <type>d:text</type>
                    <mandatory>false</mandatory>
                    <index enabled="true">
                        <tokenised>TRUE</tokenised>
                        <facetable>false</facetable>
                    </index>
                </property>
            </properties>
            <associations/>
            <overrides/>
            <mandatory-aspects/>
        </aspect>
    </aspects>
</model>